rref/__init__.py
rref/main.py
rref/helpers/__init__.py
rref/helpers/math_.py
rref/helpers/mm.py
rref/helpers/utils_.py
rref-0.3.1.dist-info/LICENSE.txt
rref-0.3.1.dist-info/METADATA
rref-0.3.1.dist-info/WHEEL
rref-0.3.1.dist-info/top_level.txt
rref-0.3.1.dist-info/RECORD
