Metadata-Version: 2.1
Name: rref
Version: 0.3.1
Summary: Package to help transform 2-D matrix into reduced row-echelon form.
Home-page: UNKNOWN
Author: Mark Moretto
Author-email: otteromkram@gmail.com
License: UNKNOWN
Project-URL: Source, https://github.com/MarkMoretto/rref
Keywords: rref,matrix,row reduced echelon form,echelon,Gaussian elimination,linear algebra
Platform: UNKNOWN
Classifier: Development Status :: 4 - Beta
Classifier: Intended Audience :: Education
Classifier: Intended Audience :: Science/Research
Classifier: Intended Audience :: Other Audience
Classifier: License :: CC0 1.0 Universal (CC0 1.0) Public Domain Dedication
Classifier: Natural Language :: English
Classifier: Programming Language :: Python :: 3
Classifier: Programming Language :: Python :: 3.6
Classifier: Programming Language :: Python :: 3.7
Classifier: Programming Language :: Python :: 3.8
Classifier: Operating System :: Microsoft :: Windows
Classifier: Topic :: Scientific/Engineering :: Image Recognition
Classifier: Topic :: Scientific/Engineering :: Information Analysis
Classifier: Topic :: Utilities
Requires-Python: >=3.6.*
